opensubmarine/__init__.py
opensubmarine/py.typed
opensubmarine/contracts/__init__.py
opensubmarine/contracts/access/__init__.py
opensubmarine/contracts/access/Ownable/__init__.py
opensubmarine/contracts/access/Ownable/contract.py
opensubmarine/contracts/access/Ownable/ownable.pyi
opensubmarine/contracts/participation/__init__.py
opensubmarine/contracts/participation/Stakable/__init__.py
opensubmarine/contracts/participation/Stakable/contract.py
opensubmarine/contracts/participation/Stakable/stakeable.pyi
opensubmarine/contracts/token/__init__.py
opensubmarine/contracts/token/ARC200/__init__.py
opensubmarine/contracts/token/ARC200/src/__init__.py
opensubmarine/contracts/token/ARC200/src/arc200.pyi
opensubmarine/contracts/token/ARC200/src/contract.py
opensubmarine/contracts/token/ARC200/src/utils.py
opensubmarine/contracts/token/ARC72/__init__.py
opensubmarine/contracts/token/ARC72/src/__init__.py
opensubmarine/contracts/token/ARC72/src/arc72.pyi
opensubmarine/contracts/token/ARC72/src/contract.py
opensubmarine/contracts/token/ARC72/src/utils.py
opensubmarine/contracts/update/__init__.py
opensubmarine/contracts/update/Upgradeable/__init__.py
opensubmarine/contracts/update/Upgradeable/contract.py
opensubmarine/contracts/update/Upgradeable/upgradable.pyi
opensubmarine/contracts/utils/__init__.py
opensubmarine/contracts/utils/introspection/__init__.py
opensubmarine/contracts/utils/introspection/arc73/__init__.py
opensubmarine/contracts/utils/introspection/arc73/arc73.pyi
opensubmarine/contracts/utils/introspection/arc73/contract.py
opensubmarine/utils/__init__.py
opensubmarine/utils/algorand.py
opensubmarine/utils/types.py
opensubmarine-0.2.2.dist-info/licenses/LICENSE
opensubmarine-0.2.2.dist-info/METADATA
opensubmarine-0.2.2.dist-info/WHEEL
opensubmarine-0.2.2.dist-info/top_level.txt
opensubmarine-0.2.2.dist-info/RECORD
