Metadata-Version: 2.4
Name: opensubmarine
Version: 0.2.2
Summary: A library for secure smart contract development on Algorand
Author-email: OpenSubmarine Team <hello@nautilus.sh>
License: MIT License
Project-URL: Homepage, https://github.com/NautilusOSS/opensubmarine-contracts
Keywords: algorand,smart-contracts,blockchain,crypto
Classifier: Programming Language :: Python :: 3
Classifier: License :: OSI Approved :: MIT License
Classifier: Operating System :: OS Independent
Classifier: Development Status :: 3 - Alpha
Classifier: Intended Audience :: Developers
Classifier: Topic :: Software Development :: Libraries :: Python Modules
Classifier: Topic :: Security
Requires-Python: >=3.7
License-File: LICENSE
Requires-Dist: py-algorand-sdk
Requires-Dist: algopy
Dynamic: license-file
